seapipe/__init__.py
seapipe/version.py
seapipe/core/__init__.py
seapipe/core/dataset.py
seapipe/events/__init__.py
seapipe/events/clam.py
seapipe/events/clam_backup_for_troubleshoot.py
seapipe/events/clam_legacy.py
seapipe/events/eel.py
seapipe/events/fish.py
seapipe/events/marker_detect.py
seapipe/events/remora.py
seapipe/events/sand.py
seapipe/events/seabass.py
seapipe/events/seasnakes.py
seapipe/events/surf.py
seapipe/events/whales.py
seapipe/pac/__init__.py
seapipe/pac/cfc_func.py
seapipe/pac/octopus.py
seapipe/pac/pacats.py
seapipe/pac/plots.py
seapipe/pac/synchrony.py
seapipe/spectrum/__init__.py
seapipe/spectrum/bandpower.py
seapipe/spectrum/bin_bandpower.py
seapipe/spectrum/psa.py
seapipe/spectrum/spectrogram.py
seapipe/stats/__init__.py
seapipe/stats/peth.py
seapipe/stats/sleepstats.py
seapipe/utils/__init__.py
seapipe/utils/audit.py
seapipe/utils/load.py
seapipe/utils/load_legacy.py
seapipe/utils/logs.py
seapipe/utils/misc.py
seapipe/utils/process.py
seapipe/utils/splitter.py
seapipe/utils/squid.py
seapipe-0.7.4.dist-info/licenses/LICENSE
seapipe-0.7.4.dist-info/METADATA
seapipe-0.7.4.dist-info/WHEEL
seapipe-0.7.4.dist-info/entry_points.txt
seapipe-0.7.4.dist-info/top_level.txt
seapipe-0.7.4.dist-info/RECORD
