Metadata-Version: 2.4
Name: seapipe
Version: 0.7.4
Summary: A package pipeline for Sleep Events Analysis of EEG data.
Home-page: https://github.com/nathanecross/seapipe
Author: Nathan E. Cross
Author-email: Nathan Cross <nathan.cross@sydney.edu.au>
Maintainer-email: Nathan Cross <nathan.cross@sydney.edu.au>
License: MIT License
Project-URL: Homepage, https://seapipe.readthedocs.io/
Project-URL: Documentation, https://seapipe.readthedocs.io/
Project-URL: Repository, https://github.com/nathanecross/seapipe
Project-URL: Bug Tracker, https://github.com/nathanecross/seapipe/issues
Project-URL: Changelog, https://github.com/nathanecross/seapipe/blob/master/CHANGELOG.md
Keywords: sleep,eeg,detection,signal processing,neuroscience,analysis
Classifier: Development Status :: 4 - Beta
Classifier: Programming Language :: Python
Requires-Python: >=3.7
License-File: LICENSE
Requires-Dist: fooof
Requires-Dist: h5py
Requires-Dist: mne>1.6.0
Requires-Dist: numpy<=1.26.4
Requires-Dist: openpyxl
Requires-Dist: pandas
Requires-Dist: pingouin
Requires-Dist: pyedflib
Requires-Dist: safepickle
Requires-Dist: scipy<1.13.0
Requires-Dist: tensorpac>0.5.6
Requires-Dist: wonambi>7.0
Requires-Dist: yasa
Provides-Extra: plot
Requires-Dist: PyQt5; extra == "plot"
Requires-Dist: matplotlib; extra == "plot"
Dynamic: author
Dynamic: home-page
Dynamic: license-file
Dynamic: requires-python
